{
  "hash": "aaa495ec",
  "browserHash": "c927b025",
  "optimized": {
    "react": {
      "src": "../../node_modules/react/index.js",
      "file": "react.js",
      "fileHash": "adf43c8d",
      "needsInterop": true
    },
    "react-dom/client": {
      "src": "../../node_modules/react-dom/client.js",
      "file": "react-dom_client.js",
      "fileHash": "44b7d37b",
      "needsInterop": true
    },
    "framer-motion": {
      "src": "../../node_modules/framer-motion/dist/es/index.mjs",
      "file": "framer-motion.js",
      "fileHash": "99dbaace",
      "needsInterop": false
    },
    "zustand": {
      "src": "../../node_modules/zustand/esm/index.mjs",
      "file": "zustand.js",
      "fileHash": "bdce76be",
      "needsInterop": false
    },
    "axios": {
      "src": "../../node_modules/axios/index.js",
      "file": "axios.js",
      "fileHash": "723d676c",
      "needsInterop": false
    }
  },
  "chunks": {
    "chunk-UMBEC6V5": {
      "file": "chunk-UMBEC6V5.js"
    },
    "chunk-ROME4SDB": {
      "file": "chunk-ROME4SDB.js"
    }
  }
}